[
  {
    "city": "香港",
    "forecast_date": "2026-06-09",
    "metric": "max_temp",
    "market_question": "Will the highest temperature in Hong Kong be 23°C or below on June 9?",
    "threshold": 23.0,
    "condition": "<=",
    "yes_price": 0.0005,
    "source": "polymarket_candidate",
    "url": "https://polymarket.com/event/highest-temperature-in-hong-kong-on-june-9-2026",
    "volume": 11126.690999999999,
    "volume24hr": 10992.688,
    "liquidity": 4826.02484,
    "raw_market_id": "2459839",
    "raw_event_id": "568044",
    "condition_reason": "包含短语 \"or below\""
  },
  {
    "city": "香港",
    "forecast_date": "2026-06-09",
    "metric": "max_temp",
    "market_question": "Will the highest temperature in Hong Kong be 24°C on June 9?",
    "threshold": 24.0,
    "condition": "=",
    "yes_price": 0.0005,
    "source": "polymarket_candidate",
    "url": "https://polymarket.com/event/highest-temperature-in-hong-kong-on-june-9-2026",
    "volume": 5711.2080000000005,
    "volume24hr": 5480.116,
    "liquidity": 10646.79366,
    "raw_market_id": "2459840",
    "raw_event_id": "568044",
    "condition_reason": "未发现 or below/or above 等方向短语，按精确温度市场处理"
  },
  {
    "city": "香港",
    "forecast_date": "2026-06-09",
    "metric": "max_temp",
    "market_question": "Will the highest temperature in Hong Kong be 25°C on June 9?",
    "threshold": 25.0,
    "condition": "=",
    "yes_price": 0.0005,
    "source": "polymarket_candidate",
    "url": "https://polymarket.com/event/highest-temperature-in-hong-kong-on-june-9-2026",
    "volume": 8099.14296,
    "volume24hr": 7240.495929,
    "liquidity": 5828.21448,
    "raw_market_id": "2459841",
    "raw_event_id": "568044",
    "condition_reason": "未发现 or below/or above 等方向短语，按精确温度市场处理"
  },
  {
    "city": "香港",
    "forecast_date": "2026-06-09",
    "metric": "max_temp",
    "market_question": "Will the highest temperature in Hong Kong be 26°C on June 9?",
    "threshold": 26.0,
    "condition": "=",
    "yes_price": 0.0005,
    "source": "polymarket_candidate",
    "url": "https://polymarket.com/event/highest-temperature-in-hong-kong-on-june-9-2026",
    "volume": 13988.035638000001,
    "volume24hr": 13012.12333,
    "liquidity": 10211.4888,
    "raw_market_id": "2459842",
    "raw_event_id": "568044",
    "condition_reason": "未发现 or below/or above 等方向短语，按精确温度市场处理"
  },
  {
    "city": "香港",
    "forecast_date": "2026-06-09",
    "metric": "max_temp",
    "market_question": "Will the highest temperature in Hong Kong be 27°C on June 9?",
    "threshold": 27.0,
    "condition": "=",
    "yes_price": 0.6935,
    "source": "polymarket_candidate",
    "url": "https://polymarket.com/event/highest-temperature-in-hong-kong-on-june-9-2026",
    "volume": 31964.838756,
    "volume24hr": 31539.069322999996,
    "liquidity": 967.43362,
    "raw_market_id": "2459843",
    "raw_event_id": "568044",
    "condition_reason": "未发现 or below/or above 等方向短语，按精确温度市场处理"
  },
  {
    "city": "香港",
    "forecast_date": "2026-06-09",
    "metric": "max_temp",
    "market_question": "Will the highest temperature in Hong Kong be 28°C on June 9?",
    "threshold": 28.0,
    "condition": "=",
    "yes_price": 0.22,
    "source": "polymarket_candidate",
    "url": "https://polymarket.com/event/highest-temperature-in-hong-kong-on-june-9-2026",
    "volume": 19040.573083000003,
    "volume24hr": 18503.419816000005,
    "liquidity": 1020.6937,
    "raw_market_id": "2459844",
    "raw_event_id": "568044",
    "condition_reason": "未发现 or below/or above 等方向短语，按精确温度市场处理"
  },
  {
    "city": "香港",
    "forecast_date": "2026-06-09",
    "metric": "max_temp",
    "market_question": "Will the highest temperature in Hong Kong be 29°C on June 9?",
    "threshold": 29.0,
    "condition": "=",
    "yes_price": 0.065,
    "source": "polymarket_candidate",
    "url": "https://polymarket.com/event/highest-temperature-in-hong-kong-on-june-9-2026",
    "volume": 18347.45542199999,
    "volume24hr": 17416.678410000004,
    "liquidity": 1772.8738,
    "raw_market_id": "2459845",
    "raw_event_id": "568044",
    "condition_reason": "未发现 or below/or above 等方向短语，按精确温度市场处理"
  },
  {
    "city": "香港",
    "forecast_date": "2026-06-09",
    "metric": "max_temp",
    "market_question": "Will the highest temperature in Hong Kong be 30°C on June 9?",
    "threshold": 30.0,
    "condition": "=",
    "yes_price": 0.0135,
    "source": "polymarket_candidate",
    "url": "https://polymarket.com/event/highest-temperature-in-hong-kong-on-june-9-2026",
    "volume": 20045.008114,
    "volume24hr": 19749.023919000003,
    "liquidity": 6166.39741,
    "raw_market_id": "2459846",
    "raw_event_id": "568044",
    "condition_reason": "未发现 or below/or above 等方向短语，按精确温度市场处理"
  },
  {
    "city": "香港",
    "forecast_date": "2026-06-09",
    "metric": "max_temp",
    "market_question": "Will the highest temperature in Hong Kong be 31°C on June 9?",
    "threshold": 31.0,
    "condition": "=",
    "yes_price": 0.0035,
    "source": "polymarket_candidate",
    "url": "https://polymarket.com/event/highest-temperature-in-hong-kong-on-june-9-2026",
    "volume": 15535.916728,
    "volume24hr": 15073.092336999998,
    "liquidity": 3533.27615,
    "raw_market_id": "2459847",
    "raw_event_id": "568044",
    "condition_reason": "未发现 or below/or above 等方向短语，按精确温度市场处理"
  },
  {
    "city": "香港",
    "forecast_date": "2026-06-09",
    "metric": "max_temp",
    "market_question": "Will the highest temperature in Hong Kong be 32°C on June 9?",
    "threshold": 32.0,
    "condition": "=",
    "yes_price": 0.0015,
    "source": "polymarket_candidate",
    "url": "https://polymarket.com/event/highest-temperature-in-hong-kong-on-june-9-2026",
    "volume": 23222.016713,
    "volume24hr": 22066.940787999993,
    "liquidity": 3822.64468,
    "raw_market_id": "2459848",
    "raw_event_id": "568044",
    "condition_reason": "未发现 or below/or above 等方向短语，按精确温度市场处理"
  },
  {
    "city": "香港",
    "forecast_date": "2026-06-09",
    "metric": "max_temp",
    "market_question": "Will the highest temperature in Hong Kong be 33°C or higher on June 9?",
    "threshold": 33.0,
    "condition": ">=",
    "yes_price": 0.0005,
    "source": "polymarket_candidate",
    "url": "https://polymarket.com/event/highest-temperature-in-hong-kong-on-june-9-2026",
    "volume": 18669.14195099999,
    "volume24hr": 17199.382474000002,
    "liquidity": 3061.93755,
    "raw_market_id": "2459849",
    "raw_event_id": "568044",
    "condition_reason": "包含短语 \"or higher\""
  }
]