[
  {
    "city": "香港",
    "matched_city_alias": "Hong Kong",
    "event_title": "Highest temperature in Hong Kong on July 2?",
    "market_question": "Will the highest temperature in Hong Kong be 31°C on July 2?",
    "slug": "highest-temperature-in-hong-kong-on-july-2-2026-31c",
    "event_slug": "highest-temperature-in-hong-kong-on-july-2-2026",
    "forecast_date": "2026-07-02",
    "condition": "=",
    "condition_reason": "未发现 or below/or above 等方向短语，按精确温度市场处理",
    "start_date": "2026-06-30T04:02:35Z",
    "end_date": "2026-07-02T12:00:00Z",
    "volume": 29503.789715999992,
    "volume24hr": 27386.119473000024,
    "liquidity": 1181.8706,
    "active": true,
    "closed": false,
    "accepting_orders": true,
    "raw_market_id": "2738625",
    "raw_event_id": "650041",
    "url": "https://polymarket.com/event/highest-temperature-in-hong-kong-on-july-2-2026",
    "metric": "max_temp",
    "threshold": 31.0,
    "yes_price": 0.125
  },
  {
    "city": "香港",
    "matched_city_alias": "Hong Kong",
    "event_title": "Highest temperature in Hong Kong on July 2?",
    "market_question": "Will the highest temperature in Hong Kong be 34°C on July 2?",
    "slug": "highest-temperature-in-hong-kong-on-july-2-2026-34c",
    "event_slug": "highest-temperature-in-hong-kong-on-july-2-2026",
    "forecast_date": "2026-07-02",
    "condition": "=",
    "condition_reason": "未发现 or below/or above 等方向短语，按精确温度市场处理",
    "start_date": "2026-06-30T04:02:35Z",
    "end_date": "2026-07-02T12:00:00Z",
    "volume": 30632.985071000003,
    "volume24hr": 26917.843448000003,
    "liquidity": 1598.72213,
    "active": true,
    "closed": false,
    "accepting_orders": true,
    "raw_market_id": "2738628",
    "raw_event_id": "650041",
    "url": "https://polymarket.com/event/highest-temperature-in-hong-kong-on-july-2-2026",
    "metric": "max_temp",
    "threshold": 34.0,
    "yes_price": 0.017
  },
  {
    "city": "香港",
    "matched_city_alias": "Hong Kong",
    "event_title": "Highest temperature in Hong Kong on July 2?",
    "market_question": "Will the highest temperature in Hong Kong be 33°C on July 2?",
    "slug": "highest-temperature-in-hong-kong-on-july-2-2026-33c",
    "event_slug": "highest-temperature-in-hong-kong-on-july-2-2026",
    "forecast_date": "2026-07-02",
    "condition": "=",
    "condition_reason": "未发现 or below/or above 等方向短语，按精确温度市场处理",
    "start_date": "2026-06-30T04:02:35Z",
    "end_date": "2026-07-02T12:00:00Z",
    "volume": 34221.34877399999,
    "volume24hr": 26155.297127,
    "liquidity": 1572.9429,
    "active": true,
    "closed": false,
    "accepting_orders": true,
    "raw_market_id": "2738627",
    "raw_event_id": "650041",
    "url": "https://polymarket.com/event/highest-temperature-in-hong-kong-on-july-2-2026",
    "metric": "max_temp",
    "threshold": 33.0,
    "yes_price": 0.155
  },
  {
    "city": "香港",
    "matched_city_alias": "Hong Kong",
    "event_title": "Highest temperature in Hong Kong on July 2?",
    "market_question": "Will the highest temperature in Hong Kong be 30°C on July 2?",
    "slug": "highest-temperature-in-hong-kong-on-july-2-2026-30c",
    "event_slug": "highest-temperature-in-hong-kong-on-july-2-2026",
    "forecast_date": "2026-07-02",
    "condition": "=",
    "condition_reason": "未发现 or below/or above 等方向短语，按精确温度市场处理",
    "start_date": "2026-06-30T04:02:35Z",
    "end_date": "2026-07-02T12:00:00Z",
    "volume": 28346.832366000006,
    "volume24hr": 25037.188431000002,
    "liquidity": 17588.0068,
    "active": true,
    "closed": false,
    "accepting_orders": true,
    "raw_market_id": "2738624",
    "raw_event_id": "650041",
    "url": "https://polymarket.com/event/highest-temperature-in-hong-kong-on-july-2-2026",
    "metric": "max_temp",
    "threshold": 30.0,
    "yes_price": 0.0005
  },
  {
    "city": "香港",
    "matched_city_alias": "Hong Kong",
    "event_title": "Highest temperature in Hong Kong on July 2?",
    "market_question": "Will the highest temperature in Hong Kong be 32°C on July 2?",
    "slug": "highest-temperature-in-hong-kong-on-july-2-2026-32c",
    "event_slug": "highest-temperature-in-hong-kong-on-july-2-2026",
    "forecast_date": "2026-07-02",
    "condition": "=",
    "condition_reason": "未发现 or below/or above 等方向短语，按精确温度市场处理",
    "start_date": "2026-06-30T04:02:35Z",
    "end_date": "2026-07-02T12:00:00Z",
    "volume": 27096.511626000043,
    "volume24hr": 23823.946554999988,
    "liquidity": 1366.2889,
    "active": true,
    "closed": false,
    "accepting_orders": true,
    "raw_market_id": "2738626",
    "raw_event_id": "650041",
    "url": "https://polymarket.com/event/highest-temperature-in-hong-kong-on-july-2-2026",
    "metric": "max_temp",
    "threshold": 32.0,
    "yes_price": 0.65
  },
  {
    "city": "香港",
    "matched_city_alias": "Hong Kong",
    "event_title": "Highest temperature in Hong Kong on July 2?",
    "market_question": "Will the highest temperature in Hong Kong be 35°C on July 2?",
    "slug": "highest-temperature-in-hong-kong-on-july-2-2026-35c",
    "event_slug": "highest-temperature-in-hong-kong-on-july-2-2026",
    "forecast_date": "2026-07-02",
    "condition": "=",
    "condition_reason": "未发现 or below/or above 等方向短语，按精确温度市场处理",
    "start_date": "2026-06-30T04:02:35Z",
    "end_date": "2026-07-02T12:00:00Z",
    "volume": 14126.557136000007,
    "volume24hr": 11757.625898999999,
    "liquidity": 2760.07574,
    "active": true,
    "closed": false,
    "accepting_orders": true,
    "raw_market_id": "2738629",
    "raw_event_id": "650041",
    "url": "https://polymarket.com/event/highest-temperature-in-hong-kong-on-july-2-2026",
    "metric": "max_temp",
    "threshold": 35.0,
    "yes_price": 0.0015
  },
  {
    "city": "香港",
    "matched_city_alias": "Hong Kong",
    "event_title": "Highest temperature in Hong Kong on July 2?",
    "market_question": "Will the highest temperature in Hong Kong be 29°C on July 2?",
    "slug": "highest-temperature-in-hong-kong-on-july-2-2026-29c",
    "event_slug": "highest-temperature-in-hong-kong-on-july-2-2026",
    "forecast_date": "2026-07-02",
    "condition": "=",
    "condition_reason": "未发现 or below/or above 等方向短语，按精确温度市场处理",
    "start_date": "2026-06-30T04:02:35Z",
    "end_date": "2026-07-02T12:00:00Z",
    "volume": 11179.468268999999,
    "volume24hr": 9580.547935999999,
    "liquidity": 10325.38956,
    "active": true,
    "closed": false,
    "accepting_orders": true,
    "raw_market_id": "2738623",
    "raw_event_id": "650041",
    "url": "https://polymarket.com/event/highest-temperature-in-hong-kong-on-july-2-2026",
    "metric": "max_temp",
    "threshold": 29.0,
    "yes_price": 0.0005
  },
  {
    "city": "香港",
    "matched_city_alias": "Hong Kong",
    "event_title": "Highest temperature in Hong Kong on July 2?",
    "market_question": "Will the highest temperature in Hong Kong be 36°C on July 2?",
    "slug": "highest-temperature-in-hong-kong-on-july-2-2026-36c",
    "event_slug": "highest-temperature-in-hong-kong-on-july-2-2026",
    "forecast_date": "2026-07-02",
    "condition": "=",
    "condition_reason": "未发现 or below/or above 等方向短语，按精确温度市场处理",
    "start_date": "2026-06-30T04:02:35Z",
    "end_date": "2026-07-02T12:00:00Z",
    "volume": 9249.626977000005,
    "volume24hr": 7539.878799000001,
    "liquidity": 2521.44854,
    "active": true,
    "closed": false,
    "accepting_orders": true,
    "raw_market_id": "2738630",
    "raw_event_id": "650041",
    "url": "https://polymarket.com/event/highest-temperature-in-hong-kong-on-july-2-2026",
    "metric": "max_temp",
    "threshold": 36.0,
    "yes_price": 0.0005
  },
  {
    "city": "香港",
    "matched_city_alias": "Hong Kong",
    "event_title": "Highest temperature in Hong Kong on July 2?",
    "market_question": "Will the highest temperature in Hong Kong be 27°C or below on July 2?",
    "slug": "highest-temperature-in-hong-kong-on-july-2-2026-27corbelow",
    "event_slug": "highest-temperature-in-hong-kong-on-july-2-2026",
    "forecast_date": "2026-07-02",
    "condition": "<=",
    "condition_reason": "包含短语 \"or below\"",
    "start_date": "2026-06-30T04:02:35Z",
    "end_date": "2026-07-02T12:00:00Z",
    "volume": 7752.899749000002,
    "volume24hr": 6382.946749,
    "liquidity": 8378.0348,
    "active": true,
    "closed": false,
    "accepting_orders": true,
    "raw_market_id": "2738621",
    "raw_event_id": "650041",
    "url": "https://polymarket.com/event/highest-temperature-in-hong-kong-on-july-2-2026",
    "metric": "max_temp",
    "threshold": 27.0,
    "yes_price": 0.0005
  },
  {
    "city": "香港",
    "matched_city_alias": "Hong Kong",
    "event_title": "Highest temperature in Hong Kong on July 2?",
    "market_question": "Will the highest temperature in Hong Kong be 37°C or higher on July 2?",
    "slug": "highest-temperature-in-hong-kong-on-july-2-2026-37corhigher",
    "event_slug": "highest-temperature-in-hong-kong-on-july-2-2026",
    "forecast_date": "2026-07-02",
    "condition": ">=",
    "condition_reason": "包含短语 \"or higher\"",
    "start_date": "2026-06-30T04:02:35Z",
    "end_date": "2026-07-02T12:00:00Z",
    "volume": 6903.951905000001,
    "volume24hr": 5525.762905,
    "liquidity": 3204.82418,
    "active": true,
    "closed": false,
    "accepting_orders": true,
    "raw_market_id": "2738631",
    "raw_event_id": "650041",
    "url": "https://polymarket.com/event/highest-temperature-in-hong-kong-on-july-2-2026",
    "metric": "max_temp",
    "threshold": 37.0,
    "yes_price": 0.001
  },
  {
    "city": "香港",
    "matched_city_alias": "Hong Kong",
    "event_title": "Highest temperature in Hong Kong on July 2?",
    "market_question": "Will the highest temperature in Hong Kong be 28°C on July 2?",
    "slug": "highest-temperature-in-hong-kong-on-july-2-2026-28c",
    "event_slug": "highest-temperature-in-hong-kong-on-july-2-2026",
    "forecast_date": "2026-07-02",
    "condition": "=",
    "condition_reason": "未发现 or below/or above 等方向短语，按精确温度市场处理",
    "start_date": "2026-06-30T04:02:35Z",
    "end_date": "2026-07-02T12:00:00Z",
    "volume": 4467.583474000001,
    "volume24hr": 3131.004474,
    "liquidity": 10099.06351,
    "active": true,
    "closed": false,
    "accepting_orders": true,
    "raw_market_id": "2738622",
    "raw_event_id": "650041",
    "url": "https://polymarket.com/event/highest-temperature-in-hong-kong-on-july-2-2026",
    "metric": "max_temp",
    "threshold": 28.0,
    "yes_price": 0.0005
  }
]